pinspect/__init__.py
pinspect/logger.py
pinspect/traverse.py
pinspect/utils.py
pinspect-0.0.2.dist-info/LICENSE
pinspect-0.0.2.dist-info/METADATA
pinspect-0.0.2.dist-info/WHEEL
pinspect-0.0.2.dist-info/top_level.txt
pinspect-0.0.2.dist-info/RECORD
