Metadata-Version: 2.1
Name: pinspect
Version: 0.0.2
Summary: Pretty inspect object
Home-page: https://github.com/dizcza/pinspect
Author: Danylo Ulianych
Author-email: d.ulianych@gmail.com
License: MIT
Platform: UNKNOWN
Classifier: Programming Language :: Python :: 3
Classifier: License :: OSI Approved :: MIT License
Classifier: Operating System :: OS Independent
Requires-Python: >=3.6
Requires-Dist: networkx (>=2.4)
Requires-Dist: pyvis (>=0.1.7.0)
Requires-Dist: tqdm
